aifail/__init__.py
aifail/aifail.py
aifail-0.3.0.dist-info/LICENSE.txt
aifail-0.3.0.dist-info/METADATA
aifail-0.3.0.dist-info/WHEEL
aifail-0.3.0.dist-info/RECORD
