Metadata-Version: 2.1
Name: aifail
Version: 0.3.0
Summary: 
Author: Dev Aggarwal
Author-email: devxpy@gmail.com
Requires-Python: >=3.10,<4.0
Classifier: Programming Language :: Python :: 3
Classifier: Programming Language :: Python :: 3.10
Classifier: Programming Language :: Python :: 3.11
Classifier: Programming Language :: Python :: 3.12
Requires-Dist: loguru (>=0.7.2,<0.8.0)
